pyro/__init__.py
pyro/_version.py
pyro/generic.py
pyro/logger.py
pyro/primitives.py
pyro/py.typed
pyro/settings.py
pyro/util.py
pyro/contrib/__init__.py
pyro/contrib/autoguide.py
pyro/contrib/minipyro.py
pyro/contrib/util.py
pyro/contrib/zuko.py
pyro/contrib/autoname/__init__.py
pyro/contrib/autoname/autoname.py
pyro/contrib/autoname/named.py
pyro/contrib/autoname/scoping.py
pyro/contrib/bnn/__init__.py
pyro/contrib/bnn/hidden_layer.py
pyro/contrib/bnn/utils.py
pyro/contrib/cevae/__init__.py
pyro/contrib/conjugate/__init__.py
pyro/contrib/conjugate/infer.py
pyro/contrib/easyguide/__init__.py
pyro/contrib/easyguide/easyguide.py
pyro/contrib/epidemiology/__init__.py
pyro/contrib/epidemiology/compartmental.py
pyro/contrib/epidemiology/distributions.py
pyro/contrib/epidemiology/models.py
pyro/contrib/epidemiology/util.py
pyro/contrib/examples/__init__.py
pyro/contrib/examples/bart.py
pyro/contrib/examples/finance.py
pyro/contrib/examples/multi_mnist.py
pyro/contrib/examples/nextstrain.py
pyro/contrib/examples/polyphonic_data_loader.py
pyro/contrib/examples/scanvi_data.py
pyro/contrib/examples/util.py
pyro/contrib/forecast/__init__.py
pyro/contrib/forecast/evaluate.py
pyro/contrib/forecast/forecaster.py
pyro/contrib/forecast/util.py
pyro/contrib/funsor/__init__.py
pyro/contrib/funsor/handlers/__init__.py
pyro/contrib/funsor/handlers/enum_messenger.py
pyro/contrib/funsor/handlers/named_messenger.py
pyro/contrib/funsor/handlers/plate_messenger.py
pyro/contrib/funsor/handlers/primitives.py
pyro/contrib/funsor/handlers/replay_messenger.py
pyro/contrib/funsor/handlers/runtime.py
pyro/contrib/funsor/handlers/trace_messenger.py
pyro/contrib/funsor/infer/__init__.py
pyro/contrib/funsor/infer/discrete.py
pyro/contrib/funsor/infer/elbo.py
pyro/contrib/funsor/infer/trace_elbo.py
pyro/contrib/funsor/infer/traceenum_elbo.py
pyro/contrib/funsor/infer/tracetmc_elbo.py
pyro/contrib/gp/__init__.py
pyro/contrib/gp/parameterized.py
pyro/contrib/gp/util.py
pyro_ppl-1.9.1.dist-info/LICENSE.md
pyro_ppl-1.9.1.dist-info/METADATA
pyro_ppl-1.9.1.dist-info/WHEEL
pyro_ppl-1.9.1.dist-info/top_level.txt
pyro_ppl-1.9.1.dist-info/RECORD
