Metadata-Version: 2.1
Name: pyro-ppl
Version: 1.9.1
Summary: A Python library for probabilistic modeling and inference
Home-page: http://pyro.ai
Author: Uber AI Labs
License: Apache 2.0
Project-URL: Documentation, https://docs.pyro.ai
Project-URL: Source, https://github.com/pyro-ppl/pyro
Keywords: machine learning statistics probabilistic programming bayesian modeling pytorch
Classifier: Intended Audience :: Developers
Classifier: Intended Audience :: Education
Classifier: Intended Audience :: Science/Research
Classifier: License :: OSI Approved :: Apache Software License
Classifier: Operating System :: POSIX :: Linux
Classifier: Operating System :: MacOS :: MacOS X
Classifier: Programming Language :: Python :: 3.8
Classifier: Programming Language :: Python :: 3.9
Classifier: Programming Language :: Python :: 3.10
Classifier: Programming Language :: Python :: 3.11
Requires-Python: >=3.8
License-File: LICENSE.md
Requires-Dist: numpy>=1.7
Requires-Dist: opt_einsum>=2.3.2
Requires-Dist: pyro-api>=0.1.1
Requires-Dist: torch>=2.0
Requires-Dist: tqdm>=4.36
Provides-Extra: extras
Requires-Dist: notebook; extra == "extras"
Requires-Dist: ipywidgets; extra == "extras"
Requires-Dist: graphviz>=0.8; extra == "extras"
Requires-Dist: matplotlib>=1.3; extra == "extras"
Requires-Dist: torchvision>=0.15.0; extra == "extras"
Requires-Dist: visdom<0.2.2,>=0.1.4; extra == "extras"
Requires-Dist: pandas; extra == "extras"
Requires-Dist: pillow>=8.3.1; extra == "extras"
Requires-Dist: scikit-learn; extra == "extras"
Requires-Dist: seaborn>=0.11.0; extra == "extras"
Requires-Dist: wget; extra == "extras"
Requires-Dist: scipy>=1.1; extra == "extras"
Provides-Extra: test
Requires-Dist: notebook; extra == "test"
Requires-Dist: ipywidgets; extra == "test"
Requires-Dist: graphviz>=0.8; extra == "test"
Requires-Dist: matplotlib>=1.3; extra == "test"
Requires-Dist: torchvision>=0.15.0; extra == "test"
Requires-Dist: visdom<0.2.2,>=0.1.4; extra == "test"
Requires-Dist: pandas; extra == "test"
Requires-Dist: pillow>=8.3.1; extra == "test"
Requires-Dist: scikit-learn; extra == "test"
Requires-Dist: seaborn>=0.11.0; extra == "test"
Requires-Dist: wget; extra == "test"
Requires-Dist: scipy>=1.1; extra == "test"
Requires-Dist: black>=21.4b0; extra == "test"
Requires-Dist: nbval; extra == "test"
Requires-Dist: pytest-cov; extra == "test"
Requires-Dist: pytest-xdist; extra == "test"
Requires-Dist: pytest>=5.0; extra == "test"
Requires-Dist: ruff; extra == "test"
Provides-Extra: profile
Requires-Dist: prettytable; extra == "profile"
Requires-Dist: pytest-benchmark; extra == "profile"
Requires-Dist: snakeviz; extra == "profile"
Provides-Extra: dev
Requires-Dist: notebook; extra == "dev"
Requires-Dist: ipywidgets; extra == "dev"
Requires-Dist: graphviz>=0.8; extra == "dev"
Requires-Dist: matplotlib>=1.3; extra == "dev"
Requires-Dist: torchvision>=0.15.0; extra == "dev"
Requires-Dist: visdom<0.2.2,>=0.1.4; extra == "dev"
Requires-Dist: pandas; extra == "dev"
Requires-Dist: pillow>=8.3.1; extra == "dev"
Requires-Dist: scikit-learn; extra == "dev"
Requires-Dist: seaborn>=0.11.0; extra == "dev"
Requires-Dist: wget; extra == "dev"
Requires-Dist: scipy>=1.1; extra == "dev"
Requires-Dist: black>=21.4b0; extra == "dev"
Requires-Dist: mypy>=0.812; extra == "dev"
Requires-Dist: nbformat; extra == "dev"
Requires-Dist: nbsphinx>=0.3.2; extra == "dev"
Requires-Dist: nbstripout; extra == "dev"
Requires-Dist: nbval; extra == "dev"
Requires-Dist: ninja; extra == "dev"
Requires-Dist: pypandoc; extra == "dev"
Requires-Dist: pytest-xdist; extra == "dev"
Requires-Dist: pytest>=5.0; extra == "dev"
Requires-Dist: ruff; extra == "dev"
Requires-Dist: sphinx; extra == "dev"
Requires-Dist: sphinx_rtd_theme; extra == "dev"
Requires-Dist: yapf; extra == "dev"
Provides-Extra: horovod
Requires-Dist: horovod[pytorch]>=0.19; extra == "horovod"
Provides-Extra: lightning
Requires-Dist: lightning; extra == "lightning"
Provides-Extra: funsor
Requires-Dist: funsor[torch]==0.4.4; extra == "funsor"
